paratest-dummy/__init__.py
paratest-dummy/dummy.py
paratest-dummy/paratest_dummy.py
paratest_dummy/__init__.py
paratest_dummy/dummy.py
paratest_dummy-0.0.8.dist-info/DESCRIPTION.rst
paratest_dummy-0.0.8.dist-info/METADATA
paratest_dummy-0.0.8.dist-info/RECORD
paratest_dummy-0.0.8.dist-info/WHEEL
paratest_dummy-0.0.8.dist-info/entry_points.txt
paratest_dummy-0.0.8.dist-info/metadata.json
paratest_dummy-0.0.8.dist-info/top_level.txt
